oriansoft/__init__.py
oriansoft/main.py
oriansoft/src/__init__.py
oriansoft/src/crop_image.py
oriansoft/src/functions.py
oriansoft-1.0.0.dist-info/LICENSE.txt
oriansoft-1.0.0.dist-info/METADATA
oriansoft-1.0.0.dist-info/WHEEL
oriansoft-1.0.0.dist-info/top_level.txt
oriansoft-1.0.0.dist-info/RECORD
