Metadata-Version: 2.2
Name: oriansoft
Version: 1.0.0
Summary: All py functions are defined in this package
Author: OrianSoft
Author-email: info@oriansoft.com
Classifier: Programming Language :: Python :: 3
Classifier: License :: OSI Approved :: MIT License
Classifier: Operating System :: OS Independent
Requires-Python: >=3.6
License-File: LICENSE.txt
Dynamic: author
Dynamic: author-email
Dynamic: classifier
Dynamic: description
Dynamic: description-content-type
Dynamic: requires-python
Dynamic: summary
